LICENSE
pydantic_orm/__init__.py
pydantic_orm-0.1.1.dist-info/LICENSE
pydantic_orm-0.1.1.dist-info/WHEEL
pydantic_orm-0.1.1.dist-info/METADATA
pydantic_orm-0.1.1.dist-info/RECORD
